{
  "$schema": "https://schema.management.azure.com/schemas/2019-04-01/uiFormDefinition.json#",
  "view": {
    "kind": "Form",
    "properties": {
      "title": "Create Virtual Network",
      "isWizard": false,
      "steps": [
        {
          "name": "vnetConfig",
          "label": "Virtual Network Configuration",
          "elements": [
            {
              "name": "location",
              "type": "Microsoft.Common.Location",
              "label": "Location",
              "toolTip": "The location for all resources."
            },
            {
              "name": "virtualNetworkName",
              "type": "Microsoft.Common.TextBox",
              "label": "Virtual Network Name",
              "toolTip": "Name of the virtual network."
            },
            {
              "name": "addressPrefix",
              "type": "Microsoft.Common.TextBox",
              "label": "Address Prefix",
              "toolTip": "Address space for the virtual network."
            },
            {
              "name": "subnetPrefix",
              "type": "Microsoft.Common.TextBox",
              "label": "Subnet Prefix",
              "toolTip": "Address prefix for the subnet."
            }
          ]
        }
      ]
    }
  }
}
